together_ai_api_helper/__init__.py
together_ai_api_helper/common.py
together_ai_api_helper/endpoints.py
together_ai_api_helper/training.py
together_ai_api_helper-0.1.1.dist-info/licenses/LICENSE
together_ai_api_helper-0.1.1.dist-info/METADATA
together_ai_api_helper-0.1.1.dist-info/WHEEL
together_ai_api_helper-0.1.1.dist-info/top_level.txt
together_ai_api_helper-0.1.1.dist-info/RECORD
