Metadata-Version: 2.4
Name: together-ai-api-helper
Version: 0.1.1
Summary: A set of utils to make Together AI API easier to use. Implements the utils for the model fine-tuning and simplified endpoint fetching. Uses the official Together AI API and builds up on it (https://github.com/togethercomputer/together-python).
Requires-Python: >=3.13
License-File: LICENSE
Requires-Dist: huggingface-hub>=0.34.4
Requires-Dist: together>=1.5.25
Provides-Extra: dev
Requires-Dist: ruff; extra == "dev"
Requires-Dist: pre-commit; extra == "dev"
Requires-Dist: mypy; extra == "dev"
Dynamic: license-file
